{
  "lastUpdated": "2026-04-13T10:42:27Z",
  "source": "Trading Economics (fallback - BigData MCP subscription expired)",
  "stats": {
    "total": 181,
    "byCountry": {
      "JP": 40,
      "CN": 25,
      "US": 74,
      "EU": 42
    },
    "byImpact": {
      "HIGH": 121,
      "MEDIUM": 45,
      "LOW": 15
    }
  },
  "events": [
    {
      "id": "JP-2026-04-13-boj-gov-ueda-speech",
      "date": "2026-04-13",
      "time": "",
      "country": "JP",
      "title": "BOJ Gov Ueda Speech",
      "impact": 3,
      "actual": "--",
      "forecast": "--",
      "previous": "--",
      "unit": "",
      "type": "central_bank",
      "source": "tradingeconomics"
    },
    {
      "id": "CN-2026-04-13-new-yuan-loans",
      "date": "2026-04-13",
      "time": "09:00",
      "country": "CN",
      "title": "New Yuan Loans",
      "impact": 3,
      "actual": "CNY2990B",
      "forecast": "CNY2250.0B",
      "previous": "CNY900B",
      "unit": "B",
      "type": "money_supply",
      "source": "tradingeconomics"
    },
    {
      "id": "CN-2026-04-13-m2-money-supply-yoy",
      "date": "2026-04-13",
      "time": "09:00",
      "country": "CN",
      "title": "M2 Money Supply YoY",
      "impact": 2,
      "actual": "8.5%",
      "forecast": "9.1%",
      "previous": "9%",
      "unit": "%",
      "type": "money_supply",
      "source": "tradingeconomics"
    },
    {
      "id": "CN-2026-04-13-outstanding-loan-growth-yoy",
      "date": "2026-04-13",
      "time": "09:00",
      "country": "CN",
      "title": "Outstanding Loan Growth YoY",
      "impact": 1,
      "actual": "5.7%",
      "forecast": "6.1%",
      "previous": "6%",
      "unit": "%",
      "type": "money_supply",
      "source": "tradingeconomics"
    },
    {
      "id": "CN-2026-04-13-total-social-financing",
      "date": "2026-04-13",
      "time": "09:00",
      "country": "CN",
      "title": "Total Social Financing",
      "impact": 3,
      "actual": "CNY5230B",
      "forecast": "CNY4910.0B",
      "previous": "CNY2380B",
      "unit": "B",
      "type": "money_supply",
      "source": "tradingeconomics"
    },
    {
      "id": "US-2026-04-13-existing-home-sales",
      "date": "2026-04-13",
      "time": "14:00",
      "country": "US",
      "title": "Existing Home Sales",
      "impact": 3,
      "actual": "3.98M",
      "forecast": "4.01M",
      "previous": "4.13M",
      "unit": "",
      "type": "housing",
      "source": "tradingeconomics"
    },
    {
      "id": "US-2026-04-13-existing-home-sales-mom",
      "date": "2026-04-13",
      "time": "14:00",
      "country": "US",
      "title": "Existing Home Sales MoM",
      "impact": 3,
      "actual": "-3.6%",
      "forecast": "-2.0%",
      "previous": "2.7%",
      "unit": "%",
      "type": "housing",
      "source": "tradingeconomics"
    },
    {
      "id": "CN-2026-04-14-balance-of-trade",
      "date": "2026-04-14",
      "time": "03:00",
      "country": "CN",
      "title": "Balance of Trade",
      "impact": 3,
      "actual": "$90.98B",
      "forecast": "--",
      "previous": "$112B",
      "unit": "B",
      "type": "trade",
      "source": "tradingeconomics"
    },
    {
      "id": "CN-2026-04-14-exports-yoy",
      "date": "2026-04-14",
      "time": "03:00",
      "country": "CN",
      "title": "Exports YoY",
      "impact": 3,
      "actual": "39.6%",
      "forecast": "--",
      "previous": "8.3%",
      "unit": "%",
      "type": "trade",
      "source": "tradingeconomics"
    },
    {
      "id": "CN-2026-04-14-imports-yoy",
      "date": "2026-04-14",
      "time": "03:00",
      "country": "CN",
      "title": "Imports YoY",
      "impact": 3,
      "actual": "13.8%",
      "forecast": "--",
      "previous": "11.1%",
      "unit": "%",
      "type": "trade",
      "source": "tradingeconomics"
    },
    {
      "id": "JP-2026-04-14-capacity-utilization-mom",
      "date": "2026-04-14",
      "time": "04:30",
      "country": "JP",
      "title": "Capacity Utilization MoM",
      "impact": 3,
      "actual": "2.9%",
      "forecast": "--",
      "previous": "1.0%",
      "unit": "%",
      "type": "manufacturing",
      "source": "tradingeconomics"
    },
    {
      "id": "JP-2026-04-14-industrial-production-mom-final",
      "date": "2026-04-14",
      "time": "04:30",
      "country": "JP",
      "title": "Industrial Production MoM Final",
      "impact": 3,
      "actual": "4.3%",
      "forecast": "--",
      "previous": "-2.1%",
      "unit": "%",
      "type": "manufacturing",
      "source": "tradingeconomics"
    },
    {
      "id": "JP-2026-04-14-industrial-production-yoy-final",
      "date": "2026-04-14",
      "time": "04:30",
      "country": "JP",
      "title": "Industrial Production YoY Final",
      "impact": 3,
      "actual": "0.7%",
      "forecast": "--",
      "previous": "0.3%",
      "unit": "%",
      "type": "manufacturing",
      "source": "tradingeconomics"
    },
    {
      "id": "US-2026-04-14-nfib-business-optimism-index",
      "date": "2026-04-14",
      "time": "10:00",
      "country": "US",
      "title": "NFIB Business Optimism Index",
      "impact": 2,
      "actual": "98.8",
      "forecast": "--",
      "previous": "98.6",
      "unit": "",
      "type": "confidence",
      "source": "tradingeconomics"
    },
    {
      "id": "US-2026-04-14-adp-employment-change-weekly",
      "date": "2026-04-14",
      "time": "12:15",
      "country": "US",
      "title": "ADP Employment Change Weekly",
      "impact": 3,
      "actual": "26K",
      "forecast": "--",
      "previous": "--",
      "unit": "K",
      "type": "employment",
      "source": "tradingeconomics"
    },
    {
      "id": "US-2026-04-14-ppi-mom",
      "date": "2026-04-14",
      "time": "12:30",
      "country": "US",
      "title": "PPI MoM",
      "impact": 3,
      "actual": "0.7%",
      "forecast": "1.3%",
      "previous": "1.2%",
      "unit": "%",
      "type": "inflation",
      "source": "tradingeconomics"
    },
    {
      "id": "US-2026-04-14-core-ppi-mom",
      "date": "2026-04-14",
      "time": "12:30",
      "country": "US",
      "title": "Core PPI MoM",
      "impact": 3,
      "actual": "0.5%",
      "forecast": "0.5%",
      "previous": "0.6%",
      "unit": "%",
      "type": "inflation",
      "source": "tradingeconomics"
    },
    {
      "id": "US-2026-04-14-core-ppi-yoy",
      "date": "2026-04-14",
      "time": "12:30",
      "country": "US",
      "title": "Core PPI YoY",
      "impact": 3,
      "actual": "3.9%",
      "forecast": "4.0%",
      "previous": "4.2%",
      "unit": "%",
      "type": "inflation",
      "source": "tradingeconomics"
    },
    {
      "id": "US-2026-04-14-ppi-yoy",
      "date": "2026-04-14",
      "time": "12:30",
      "country": "US",
      "title": "PPI YoY",
      "impact": 3,
      "actual": "3.4%",
      "forecast": "4.4%",
      "previous": "4.6%",
      "unit": "%",
      "type": "inflation",
      "source": "tradingeconomics"
    },
    {
      "id": "JP-2026-04-14-machinery-orders-mom",
      "date": "2026-04-14",
      "time": "23:50",
      "country": "JP",
      "title": "Machinery Orders MoM",
      "impact": 3,
      "actual": "-5.5%",
      "forecast": "7.0%",
      "previous": "-1.1%",
      "unit": "%",
      "type": "other",
      "source": "tradingeconomics"
    },
    {
      "id": "JP-2026-04-14-machinery-orders-yoy",
      "date": "2026-04-14",
      "time": "23:50",
      "country": "JP",
      "title": "Machinery Orders YoY",
      "impact": 3,
      "actual": "13.7%",
      "forecast": "15.0%",
      "previous": "8.5%",
      "unit": "%",
      "type": "other",
      "source": "tradingeconomics"
    },
    {
      "id": "EU-2026-04-15-industrial-production-mom",
      "date": "2026-04-15",
      "time": "09:00",
      "country": "EU",
      "title": "Industrial Production MoM",
      "impact": 3,
      "actual": "-1.5%",
      "forecast": "0.5%",
      "previous": "0.3%",
      "unit": "%",
      "type": "manufacturing",
      "source": "tradingeconomics"
    },
    {
      "id": "EU-2026-04-15-industrial-production-yoy",
      "date": "2026-04-15",
      "time": "09:00",
      "country": "EU",
      "title": "Industrial Production YoY",
      "impact": 3,
      "actual": "-1.2%",
      "forecast": "-1.2%",
      "previous": "-1.4%",
      "unit": "%",
      "type": "manufacturing",
      "source": "tradingeconomics"
    },
    {
      "id": "US-2026-04-15-export-prices-mom",
      "date": "2026-04-15",
      "time": "12:30",
      "country": "US",
      "title": "Export Prices MoM",
      "impact": 2,
      "actual": "1.5%",
      "forecast": "2.2%",
      "previous": "1.8%",
      "unit": "%",
      "type": "inflation",
      "source": "tradingeconomics"
    },
    {
      "id": "US-2026-04-15-import-prices-mom",
      "date": "2026-04-15",
      "time": "12:30",
      "country": "US",
      "title": "Import Prices MoM",
      "impact": 2,
      "actual": "1.3%",
      "forecast": "1.9%",
      "previous": "2.0%",
      "unit": "%",
      "type": "inflation",
      "source": "tradingeconomics"
    },
    {
      "id": "US-2026-04-15-ny-empire-state-manufacturing-index",
      "date": "2026-04-15",
      "time": "12:30",
      "country": "US",
      "title": "NY Empire State Manufacturing Index",
      "impact": 2,
      "actual": "-0.20",
      "forecast": "-3.1",
      "previous": "-2",
      "unit": "",
      "type": "manufacturing",
      "source": "tradingeconomics"
    },
    {
      "id": "US-2026-04-15-nahb-housing-market-index",
      "date": "2026-04-15",
      "time": "14:00",
      "country": "US",
      "title": "NAHB Housing Market Index",
      "impact": 2,
      "actual": "38",
      "forecast": "37",
      "previous": "38",
      "unit": "",
      "type": "housing",
      "source": "tradingeconomics"
    },
    {
      "id": "US-2026-04-15-fed-beige-book",
      "date": "2026-04-15",
      "time": "18:00",
      "country": "US",
      "title": "Fed Beige Book",
      "impact": 2,
      "actual": "--",
      "forecast": "--",
      "previous": "--",
      "unit": "",
      "type": "central_bank",
      "source": "tradingeconomics"
    },
    {
      "id": "US-2026-04-15-net-long-term-tic-flows",
      "date": "2026-04-15",
      "time": "20:00",
      "country": "US",
      "title": "Net Long-term TIC Flows",
      "impact": 2,
      "actual": "$15.5B",
      "forecast": "--",
      "previous": "$58.6B",
      "unit": "B",
      "type": "trade",
      "source": "tradingeconomics"
    },
    {
      "id": "JP-2026-04-15-reuters-tankan-index",
      "date": "2026-04-15",
      "time": "23:00",
      "country": "JP",
      "title": "Reuters Tankan Index",
      "impact": 2,
      "actual": "18",
      "forecast": "--",
      "previous": "15",
      "unit": "",
      "type": "confidence",
      "source": "tradingeconomics"
    },
    {
      "id": "CN-2026-04-16-house-price-index-yoy",
      "date": "2026-04-16",
      "time": "01:30",
      "country": "CN",
      "title": "House Price Index YoY",
      "impact": 2,
      "actual": "-3.2%",
      "forecast": "--",
      "previous": "-3.5%",
      "unit": "%",
      "type": "inflation",
      "source": "tradingeconomics"
    },
    {
      "id": "CN-2026-04-16-gdp-growth-rate-yoy",
      "date": "2026-04-16",
      "time": "02:00",
      "country": "CN",
      "title": "GDP Growth Rate YoY",
      "impact": 3,
      "actual": "4.5%",
      "forecast": "5.2%",
      "previous": "4.8%",
      "unit": "%",
      "type": "gdp",
      "source": "tradingeconomics"
    },
    {
      "id": "CN-2026-04-16-gdp-growth-rate-qoq",
      "date": "2026-04-16",
      "time": "02:00",
      "country": "CN",
      "title": "GDP Growth Rate QoQ",
      "impact": 3,
      "actual": "1.2%",
      "forecast": "1.6%",
      "previous": "1.4%",
      "unit": "%",
      "type": "gdp",
      "source": "tradingeconomics"
    },
    {
      "id": "CN-2026-04-16-industrial-production-yoy",
      "date": "2026-04-16",
      "time": "02:00",
      "country": "CN",
      "title": "Industrial Production YoY",
      "impact": 3,
      "actual": "6.3%",
      "forecast": "5.4%",
      "previous": "5.6%",
      "unit": "%",
      "type": "manufacturing",
      "source": "tradingeconomics"
    },
    {
      "id": "CN-2026-04-16-retail-sales-yoy",
      "date": "2026-04-16",
      "time": "02:00",
      "country": "CN",
      "title": "Retail Sales YoY",
      "impact": 2,
      "actual": "2.8%",
      "forecast": "3.5%",
      "previous": "2.3%",
      "unit": "%",
      "type": "consumer",
      "source": "tradingeconomics"
    },
    {
      "id": "CN-2026-04-16-fixed-asset-investment-ytd-yoy",
      "date": "2026-04-16",
      "time": "02:00",
      "country": "CN",
      "title": "Fixed Asset Investment YTD YoY",
      "impact": 3,
      "actual": "1.8%",
      "forecast": "2.0%",
      "previous": "1.9%",
      "unit": "%",
      "type": "other",
      "source": "tradingeconomics"
    },
    {
      "id": "CN-2026-04-16-unemployment-rate",
      "date": "2026-04-16",
      "time": "02:00",
      "country": "CN",
      "title": "Unemployment Rate",
      "impact": 3,
      "actual": "5.3%",
      "forecast": "5.20%",
      "previous": "5.2%",
      "unit": "%",
      "type": "employment",
      "source": "tradingeconomics"
    },
    {
      "id": "EU-2026-04-16-core-inflation-rate-yoy-final",
      "date": "2026-04-16",
      "time": "09:00",
      "country": "EU",
      "title": "Core Inflation Rate YoY Final",
      "impact": 3,
      "actual": "2.4%",
      "forecast": "2.3%",
      "previous": "2.3%",
      "unit": "%",
      "type": "inflation",
      "source": "tradingeconomics"
    },
    {
      "id": "EU-2026-04-16-inflation-rate-mom-final",
      "date": "2026-04-16",
      "time": "09:00",
      "country": "EU",
      "title": "Inflation Rate MoM Final",
      "impact": 3,
      "actual": "0.6%",
      "forecast": "1.2%",
      "previous": "1.2%",
      "unit": "%",
      "type": "inflation",
      "source": "tradingeconomics"
    },
    {
      "id": "EU-2026-04-16-inflation-rate-yoy-final",
      "date": "2026-04-16",
      "time": "09:00",
      "country": "EU",
      "title": "Inflation Rate YoY Final",
      "impact": 3,
      "actual": "1.9%",
      "forecast": "2.5%",
      "previous": "2.5%",
      "unit": "%",
      "type": "inflation",
      "source": "tradingeconomics"
    },
    {
      "id": "EU-2026-04-16-ecb-monetary-policy-meeting-accounts",
      "date": "2026-04-16",
      "time": "11:30",
      "country": "EU",
      "title": "ECB Monetary Policy Meeting Accounts",
      "impact": 3,
      "actual": "--",
      "forecast": "--",
      "previous": "--",
      "unit": "",
      "type": "central_bank",
      "source": "tradingeconomics"
    },
    {
      "id": "US-2026-04-16-initial-jobless-claims",
      "date": "2026-04-16",
      "time": "12:30",
      "country": "US",
      "title": "Initial Jobless Claims",
      "impact": 3,
      "actual": "219K",
      "forecast": "216.0K",
      "previous": "215K",
      "unit": "K",
      "type": "employment",
      "source": "tradingeconomics"
    },
    {
      "id": "US-2026-04-16-philadelphia-fed-manufacturing-index",
      "date": "2026-04-16",
      "time": "12:30",
      "country": "US",
      "title": "Philadelphia Fed Manufacturing Index",
      "impact": 3,
      "actual": "18.1",
      "forecast": "17",
      "previous": "9",
      "unit": "",
      "type": "central_bank",
      "source": "tradingeconomics"
    },
    {
      "id": "US-2026-04-16-continuing-jobless-claims",
      "date": "2026-04-16",
      "time": "12:30",
      "country": "US",
      "title": "Continuing Jobless Claims",
      "impact": 1,
      "actual": "1794K",
      "forecast": "1840.0K",
      "previous": "--",
      "unit": "K",
      "type": "employment",
      "source": "tradingeconomics"
    },
    {
      "id": "US-2026-04-16-industrial-production-mom",
      "date": "2026-04-16",
      "time": "13:15",
      "country": "US",
      "title": "Industrial Production MoM",
      "impact": 3,
      "actual": "0.2%",
      "forecast": "0.5%",
      "previous": "0.1%",
      "unit": "%",
      "type": "manufacturing",
      "source": "tradingeconomics"
    },
    {
      "id": "US-2026-04-16-capacity-utilization",
      "date": "2026-04-16",
      "time": "13:15",
      "country": "US",
      "title": "Capacity Utilization",
      "impact": 3,
      "actual": "76.3%",
      "forecast": "76.4%",
      "previous": "76.3%",
      "unit": "%",
      "type": "manufacturing",
      "source": "tradingeconomics"
    },
    {
      "id": "US-2026-04-16-manufacturing-production-mom",
      "date": "2026-04-16",
      "time": "13:15",
      "country": "US",
      "title": "Manufacturing Production MoM",
      "impact": 1,
      "actual": "0.2%",
      "forecast": "0.5%",
      "previous": "0.1%",
      "unit": "%",
      "type": "manufacturing",
      "source": "tradingeconomics"
    },
    {
      "id": "EU-2026-04-17-current-account",
      "date": "2026-04-17",
      "time": "08:00",
      "country": "EU",
      "title": "Current Account",
      "impact": 2,
      "actual": "€13B",
      "forecast": "€16.0B",
      "previous": "--",
      "unit": "B",
      "type": "trade",
      "source": "tradingeconomics"
    },
    {
      "id": "EU-2026-04-17-current-account-s-a",
      "date": "2026-04-17",
      "time": "08:00",
      "country": "EU",
      "title": "Current Account s.a.",
      "impact": 2,
      "actual": "€37.9B",
      "forecast": "€29.0B",
      "previous": "€27.6B",
      "unit": "B",
      "type": "trade",
      "source": "tradingeconomics"
    },
    {
      "id": "EU-2026-04-17-balance-of-trade",
      "date": "2026-04-17",
      "time": "09:00",
      "country": "EU",
      "title": "Balance of Trade",
      "impact": 3,
      "actual": "€-1.9B",
      "forecast": "€9.8B",
      "previous": "€11.1B",
      "unit": "B",
      "type": "trade",
      "source": "tradingeconomics"
    },
    {
      "id": "CN-2026-04-20-loan-prime-rate-1y",
      "date": "2026-04-20",
      "time": "01:15",
      "country": "CN",
      "title": "Loan Prime Rate 1Y",
      "impact": 3,
      "actual": "3%",
      "forecast": "3.0%",
      "previous": "--",
      "unit": "%",
      "type": "central_bank",
      "source": "tradingeconomics"
    },
    {
      "id": "CN-2026-04-20-loan-prime-rate-5y",
      "date": "2026-04-20",
      "time": "01:15",
      "country": "CN",
      "title": "Loan Prime Rate 5Y",
      "impact": 3,
      "actual": "3.5%",
      "forecast": "3.5%",
      "previous": "--",
      "unit": "%",
      "type": "central_bank",
      "source": "tradingeconomics"
    },
    {
      "id": "JP-2026-04-20-tertiary-industry-index-mom",
      "date": "2026-04-20",
      "time": "04:45",
      "country": "JP",
      "title": "Tertiary Industry Index MoM",
      "impact": 2,
      "actual": "1.7%",
      "forecast": "9.6%",
      "previous": "--",
      "unit": "%",
      "type": "other",
      "source": "tradingeconomics"
    },
    {
      "id": "EU-2026-04-20-construction-output-yoy",
      "date": "2026-04-20",
      "time": "09:00",
      "country": "EU",
      "title": "Construction Output YoY",
      "impact": 2,
      "actual": "-1.9%",
      "forecast": "-1.2%",
      "previous": "--",
      "unit": "%",
      "type": "housing",
      "source": "tradingeconomics"
    },
    {
      "id": "JP-2026-04-20-balance-of-trade",
      "date": "2026-04-20",
      "time": "23:50",
      "country": "JP",
      "title": "Balance of Trade",
      "impact": 3,
      "actual": "¥57.3B",
      "forecast": "¥470B",
      "previous": "--",
      "unit": "B",
      "type": "trade",
      "source": "tradingeconomics"
    },
    {
      "id": "JP-2026-04-20-exports-yoy",
      "date": "2026-04-20",
      "time": "23:50",
      "country": "JP",
      "title": "Exports YoY",
      "impact": 3,
      "actual": "4.2%",
      "forecast": "--",
      "previous": "--",
      "unit": "%",
      "type": "trade",
      "source": "tradingeconomics"
    },
    {
      "id": "JP-2026-04-20-imports-yoy",
      "date": "2026-04-20",
      "time": "23:50",
      "country": "JP",
      "title": "Imports YoY",
      "impact": 3,
      "actual": "10.2%",
      "forecast": "--",
      "previous": "--",
      "unit": "%",
      "type": "trade",
      "source": "tradingeconomics"
    },
    {
      "id": "EU-2026-04-21-zew-economic-sentiment-index",
      "date": "2026-04-21",
      "time": "09:00",
      "country": "EU",
      "title": "ZEW Economic Sentiment Index",
      "impact": 3,
      "actual": "-8.5",
      "forecast": "-16",
      "previous": "--",
      "unit": "",
      "type": "confidence",
      "source": "tradingeconomics"
    },
    {
      "id": "US-2026-04-21-retail-sales-mom",
      "date": "2026-04-21",
      "time": "12:30",
      "country": "US",
      "title": "Retail Sales MoM",
      "impact": 3,
      "actual": "0.6%",
      "forecast": "0.4%",
      "previous": "--",
      "unit": "%",
      "type": "consumer",
      "source": "tradingeconomics"
    },
    {
      "id": "US-2026-04-21-retail-sales-ex-autos-mom",
      "date": "2026-04-21",
      "time": "12:30",
      "country": "US",
      "title": "Retail Sales Ex Autos MoM",
      "impact": 2,
      "actual": "0.5%",
      "forecast": "0.3%",
      "previous": "--",
      "unit": "%",
      "type": "consumer",
      "source": "tradingeconomics"
    },
    {
      "id": "US-2026-04-21-retail-sales-yoy",
      "date": "2026-04-21",
      "time": "12:30",
      "country": "US",
      "title": "Retail Sales YoY",
      "impact": 2,
      "actual": "3.7%",
      "forecast": "2.4%",
      "previous": "--",
      "unit": "%",
      "type": "consumer",
      "source": "tradingeconomics"
    },
    {
      "id": "US-2026-04-21-pending-home-sales-mom",
      "date": "2026-04-21",
      "time": "14:00",
      "country": "US",
      "title": "Pending Home Sales MoM",
      "impact": 2,
      "actual": "1.8%",
      "forecast": "--",
      "previous": "--",
      "unit": "%",
      "type": "housing",
      "source": "tradingeconomics"
    },
    {
      "id": "US-2026-04-21-business-inventories-mom",
      "date": "2026-04-21",
      "time": "14:00",
      "country": "US",
      "title": "Business Inventories MoM",
      "impact": 2,
      "actual": "-0.1%",
      "forecast": "0.1%",
      "previous": "--",
      "unit": "%",
      "type": "other",
      "source": "tradingeconomics"
    },
    {
      "id": "EU-2026-04-22-government-budget-to-gdp",
      "date": "2026-04-22",
      "time": "09:00",
      "country": "EU",
      "title": "Government Budget to GDP",
      "impact": 3,
      "actual": "-3.1%",
      "forecast": "-3.2%",
      "previous": "--",
      "unit": "%",
      "type": "gdp",
      "source": "tradingeconomics"
    },
    {
      "id": "EU-2026-04-22-government-debt-to-gdp",
      "date": "2026-04-22",
      "time": "09:00",
      "country": "EU",
      "title": "Government Debt to GDP",
      "impact": 3,
      "actual": "87.1%",
      "forecast": "87.6%",
      "previous": "--",
      "unit": "%",
      "type": "gdp",
      "source": "tradingeconomics"
    },
    {
      "id": "EU-2026-04-22-consumer-confidence-flash",
      "date": "2026-04-22",
      "time": "14:00",
      "country": "EU",
      "title": "Consumer Confidence Flash",
      "impact": 3,
      "actual": "-16.3",
      "forecast": "-17.9",
      "previous": "--",
      "unit": "",
      "type": "confidence",
      "source": "tradingeconomics"
    },
    {
      "id": "EU-2026-04-23-ecb-wage-tracker",
      "date": "2026-04-23",
      "time": "",
      "country": "EU",
      "title": "ECB Wage Tracker",
      "impact": 2,
      "actual": "2.7%",
      "forecast": "2.6%",
      "previous": "--",
      "unit": "%",
      "type": "central_bank",
      "source": "tradingeconomics"
    },
    {
      "id": "JP-2026-04-23-s-p-global-manufacturing-pmi-flash",
      "date": "2026-04-23",
      "time": "00:30",
      "country": "JP",
      "title": "S&P Global Manufacturing PMI Flash",
      "impact": 3,
      "actual": "51.6",
      "forecast": "--",
      "previous": "50.1",
      "unit": "",
      "type": "manufacturing",
      "source": "tradingeconomics"
    },
    {
      "id": "JP-2026-04-23-s-p-global-services-pmi-flash",
      "date": "2026-04-23",
      "time": "00:30",
      "country": "JP",
      "title": "S&P Global Services PMI Flash",
      "impact": 3,
      "actual": "53.4",
      "forecast": "--",
      "previous": "52",
      "unit": "",
      "type": "manufacturing",
      "source": "tradingeconomics"
    },
    {
      "id": "JP-2026-04-23-s-p-global-composite-pmi-flash",
      "date": "2026-04-23",
      "time": "00:30",
      "country": "JP",
      "title": "S&P Global Composite PMI Flash",
      "impact": 3,
      "actual": "53.0",
      "forecast": "--",
      "previous": "51.4",
      "unit": "",
      "type": "manufacturing",
      "source": "tradingeconomics"
    },
    {
      "id": "EU-2026-04-23-s-p-global-composite-pmi-flash",
      "date": "2026-04-23",
      "time": "08:00",
      "country": "EU",
      "title": "S&P Global Composite PMI Flash",
      "impact": 3,
      "actual": "50.7",
      "forecast": "50.2",
      "previous": "--",
      "unit": "",
      "type": "manufacturing",
      "source": "tradingeconomics"
    },
    {
      "id": "EU-2026-04-23-s-p-global-manufacturing-pmi-flash",
      "date": "2026-04-23",
      "time": "08:00",
      "country": "EU",
      "title": "S&P Global Manufacturing PMI Flash",
      "impact": 3,
      "actual": "51.6",
      "forecast": "52",
      "previous": "--",
      "unit": "",
      "type": "manufacturing",
      "source": "tradingeconomics"
    },
    {
      "id": "EU-2026-04-23-s-p-global-services-pmi-flash",
      "date": "2026-04-23",
      "time": "08:00",
      "country": "EU",
      "title": "S&P Global Services PMI Flash",
      "impact": 3,
      "actual": "50.2",
      "forecast": "49.7",
      "previous": "--",
      "unit": "",
      "type": "manufacturing",
      "source": "tradingeconomics"
    },
    {
      "id": "US-2026-04-23-chicago-fed-national-activity-index",
      "date": "2026-04-23",
      "time": "12:30",
      "country": "US",
      "title": "Chicago Fed National Activity Index",
      "impact": 1,
      "actual": "-0.11",
      "forecast": "-0.2",
      "previous": "--",
      "unit": "",
      "type": "central_bank",
      "source": "tradingeconomics"
    },
    {
      "id": "US-2026-04-23-initial-jobless-claims",
      "date": "2026-04-23",
      "time": "12:30",
      "country": "US",
      "title": "Initial Jobless Claims",
      "impact": 3,
      "actual": "--",
      "forecast": "--",
      "previous": "--",
      "unit": "",
      "type": "employment",
      "source": "tradingeconomics"
    },
    {
      "id": "US-2026-04-23-s-p-global-composite-pmi-flash",
      "date": "2026-04-23",
      "time": "13:45",
      "country": "US",
      "title": "S&P Global Composite PMI Flash",
      "impact": 3,
      "actual": "50.3",
      "forecast": "--",
      "previous": "--",
      "unit": "",
      "type": "manufacturing",
      "source": "tradingeconomics"
    },
    {
      "id": "US-2026-04-23-s-p-global-manufacturing-pmi-flash",
      "date": "2026-04-23",
      "time": "13:45",
      "country": "US",
      "title": "S&P Global Manufacturing PMI Flash",
      "impact": 3,
      "actual": "52.3",
      "forecast": "--",
      "previous": "--",
      "unit": "",
      "type": "manufacturing",
      "source": "tradingeconomics"
    },
    {
      "id": "JP-2026-04-23-inflation-rate-yoy",
      "date": "2026-04-23",
      "time": "23:30",
      "country": "JP",
      "title": "Inflation Rate YoY",
      "impact": 3,
      "actual": "1.3%",
      "forecast": "1.5%",
      "previous": "--",
      "unit": "%",
      "type": "inflation",
      "source": "tradingeconomics"
    },
    {
      "id": "JP-2026-04-23-core-inflation-rate-yoy",
      "date": "2026-04-23",
      "time": "23:30",
      "country": "JP",
      "title": "Core Inflation Rate YoY",
      "impact": 3,
      "actual": "1.6%",
      "forecast": "2.0%",
      "previous": "--",
      "unit": "%",
      "type": "inflation",
      "source": "tradingeconomics"
    },
    {
      "id": "JP-2026-04-23-inflation-rate-mom",
      "date": "2026-04-23",
      "time": "23:30",
      "country": "JP",
      "title": "Inflation Rate MoM",
      "impact": 3,
      "actual": "-0.2%",
      "forecast": "0.2%",
      "previous": "--",
      "unit": "%",
      "type": "inflation",
      "source": "tradingeconomics"
    },
    {
      "id": "US-2026-04-24-michigan-consumer-sentiment-final",
      "date": "2026-04-24",
      "time": "14:00",
      "country": "US",
      "title": "Michigan Consumer Sentiment Final",
      "impact": 3,
      "actual": "53.3",
      "forecast": "47.6",
      "previous": "47.6",
      "unit": "",
      "type": "confidence",
      "source": "tradingeconomics"
    },
    {
      "id": "US-2026-04-24-michigan-inflation-expectations-final",
      "date": "2026-04-24",
      "time": "14:00",
      "country": "US",
      "title": "Michigan Inflation Expectations Final",
      "impact": 1,
      "actual": "3.8%",
      "forecast": "4.8%",
      "previous": "4.8%",
      "unit": "%",
      "type": "inflation",
      "source": "tradingeconomics"
    },
    {
      "id": "US-2026-04-24-michigan-5-year-inflation-expectations-final",
      "date": "2026-04-24",
      "time": "14:00",
      "country": "US",
      "title": "Michigan 5 Year Inflation Expectations Final",
      "impact": 1,
      "actual": "3.2%",
      "forecast": "--",
      "previous": "--",
      "unit": "%",
      "type": "inflation",
      "source": "tradingeconomics"
    },
    {
      "id": "JP-2026-04-24-tokyo-core-cpi-yoy",
      "date": "2026-04-24",
      "time": "23:30",
      "country": "JP",
      "title": "Tokyo Core CPI YoY",
      "impact": 3,
      "actual": "1.7%",
      "forecast": "1.5%",
      "previous": "--",
      "unit": "%",
      "type": "inflation",
      "source": "tradingeconomics"
    },
    {
      "id": "JP-2026-04-24-tokyo-cpi-yoy",
      "date": "2026-04-24",
      "time": "23:30",
      "country": "JP",
      "title": "Tokyo CPI YoY",
      "impact": 3,
      "actual": "1.4%",
      "forecast": "--",
      "previous": "--",
      "unit": "%",
      "type": "inflation",
      "source": "tradingeconomics"
    },
    {
      "id": "CN-2026-04-27-industrial-profits-yoy",
      "date": "2026-04-27",
      "time": "09:00",
      "country": "CN",
      "title": "Industrial Profits YoY",
      "impact": 1,
      "actual": "--",
      "forecast": "--",
      "previous": "--",
      "unit": "",
      "type": "other",
      "source": "tradingeconomics"
    },
    {
      "id": "US-2026-04-27-dallas-fed-manufacturing-index",
      "date": "2026-04-27",
      "time": "14:30",
      "country": "US",
      "title": "Dallas Fed Manufacturing Index",
      "impact": 2,
      "actual": "-0.2",
      "forecast": "-0.8",
      "previous": "--",
      "unit": "",
      "type": "central_bank",
      "source": "tradingeconomics"
    },
    {
      "id": "JP-2026-04-28-boj-interest-rate-decision",
      "date": "2026-04-28",
      "time": "03:00",
      "country": "JP",
      "title": "BoJ Interest Rate Decision",
      "impact": 3,
      "actual": "0.75%",
      "forecast": "0.75%",
      "previous": "--",
      "unit": "%",
      "type": "central_bank",
      "source": "tradingeconomics"
    },
    {
      "id": "JP-2026-04-28-boj-quarterly-outlook-report",
      "date": "2026-04-28",
      "time": "03:00",
      "country": "JP",
      "title": "BoJ Quarterly Outlook Report",
      "impact": 3,
      "actual": "--",
      "forecast": "--",
      "previous": "--",
      "unit": "",
      "type": "central_bank",
      "source": "tradingeconomics"
    },
    {
      "id": "US-2026-04-28-s-p-case-shiller-home-price-yoy",
      "date": "2026-04-28",
      "time": "13:00",
      "country": "US",
      "title": "S&P/Case-Shiller Home Price YoY",
      "impact": 2,
      "actual": "1.2%",
      "forecast": "1.1%",
      "previous": "--",
      "unit": "%",
      "type": "housing",
      "source": "tradingeconomics"
    },
    {
      "id": "US-2026-04-28-cb-consumer-confidence",
      "date": "2026-04-28",
      "time": "14:00",
      "country": "US",
      "title": "CB Consumer Confidence",
      "impact": 3,
      "actual": "91.8",
      "forecast": "--",
      "previous": "--",
      "unit": "",
      "type": "confidence",
      "source": "tradingeconomics"
    },
    {
      "id": "US-2026-04-28-richmond-fed-manufacturing-index",
      "date": "2026-04-28",
      "time": "14:00",
      "country": "US",
      "title": "Richmond Fed Manufacturing Index",
      "impact": 2,
      "actual": "0",
      "forecast": "--",
      "previous": "--",
      "unit": "",
      "type": "central_bank",
      "source": "tradingeconomics"
    },
    {
      "id": "EU-2026-04-29-ecb-consumer-inflation-expectations",
      "date": "2026-04-29",
      "time": "",
      "country": "EU",
      "title": "ECB Consumer Inflation Expectations",
      "impact": 2,
      "actual": "2.5%",
      "forecast": "2.9%",
      "previous": "--",
      "unit": "%",
      "type": "inflation",
      "source": "tradingeconomics"
    },
    {
      "id": "JP-2026-04-29-housing-starts-yoy",
      "date": "2026-04-29",
      "time": "05:00",
      "country": "JP",
      "title": "Housing Starts YoY",
      "impact": 3,
      "actual": "-4.9%",
      "forecast": "5%",
      "previous": "--",
      "unit": "%",
      "type": "housing",
      "source": "tradingeconomics"
    },
    {
      "id": "JP-2026-04-29-construction-orders-yoy",
      "date": "2026-04-29",
      "time": "05:00",
      "country": "JP",
      "title": "Construction Orders YoY",
      "impact": 2,
      "actual": "42.7%",
      "forecast": "-4%",
      "previous": "--",
      "unit": "%",
      "type": "housing",
      "source": "tradingeconomics"
    },
    {
      "id": "EU-2026-04-29-loans-to-companies-yoy",
      "date": "2026-04-29",
      "time": "08:00",
      "country": "EU",
      "title": "Loans to Companies YoY",
      "impact": 2,
      "actual": "2.9%",
      "forecast": "2.8%",
      "previous": "--",
      "unit": "%",
      "type": "money_supply",
      "source": "tradingeconomics"
    },
    {
      "id": "EU-2026-04-29-loans-to-households-yoy",
      "date": "2026-04-29",
      "time": "08:00",
      "country": "EU",
      "title": "Loans to Households YoY",
      "impact": 2,
      "actual": "3%",
      "forecast": "2.9%",
      "previous": "--",
      "unit": "%",
      "type": "money_supply",
      "source": "tradingeconomics"
    },
    {
      "id": "EU-2026-04-29-m3-money-supply-yoy",
      "date": "2026-04-29",
      "time": "08:00",
      "country": "EU",
      "title": "M3 Money Supply YoY",
      "impact": 2,
      "actual": "3%",
      "forecast": "2.9%",
      "previous": "--",
      "unit": "%",
      "type": "money_supply",
      "source": "tradingeconomics"
    },
    {
      "id": "EU-2026-04-29-economic-sentiment",
      "date": "2026-04-29",
      "time": "09:00",
      "country": "EU",
      "title": "Economic Sentiment",
      "impact": 2,
      "actual": "96.6",
      "forecast": "95.5",
      "previous": "--",
      "unit": "",
      "type": "confidence",
      "source": "tradingeconomics"
    },
    {
      "id": "EU-2026-04-29-consumer-confidence-final",
      "date": "2026-04-29",
      "time": "09:00",
      "country": "EU",
      "title": "Consumer Confidence Final",
      "impact": 3,
      "actual": "-16.3",
      "forecast": "--",
      "previous": "--",
      "unit": "",
      "type": "confidence",
      "source": "tradingeconomics"
    },
    {
      "id": "EU-2026-04-29-consumer-inflation-expectations",
      "date": "2026-04-29",
      "time": "09:00",
      "country": "EU",
      "title": "Consumer Inflation Expectations",
      "impact": 2,
      "actual": "43.4",
      "forecast": "48",
      "previous": "--",
      "unit": "",
      "type": "inflation",
      "source": "tradingeconomics"
    },
    {
      "id": "EU-2026-04-29-industrial-sentiment",
      "date": "2026-04-29",
      "time": "09:00",
      "country": "EU",
      "title": "Industrial Sentiment",
      "impact": 1,
      "actual": "-7.0",
      "forecast": "-8",
      "previous": "--",
      "unit": "",
      "type": "confidence",
      "source": "tradingeconomics"
    },
    {
      "id": "EU-2026-04-29-services-sentiment",
      "date": "2026-04-29",
      "time": "09:00",
      "country": "EU",
      "title": "Services Sentiment",
      "impact": 2,
      "actual": "4.9",
      "forecast": "4.1",
      "previous": "--",
      "unit": "",
      "type": "confidence",
      "source": "tradingeconomics"
    },
    {
      "id": "US-2026-04-29-building-permits-prel",
      "date": "2026-04-29",
      "time": "12:30",
      "country": "US",
      "title": "Building Permits Prel",
      "impact": 3,
      "actual": "--",
      "forecast": "1.35M",
      "previous": "--",
      "unit": "",
      "type": "housing",
      "source": "tradingeconomics"
    },
    {
      "id": "US-2026-04-29-durable-goods-orders-mom",
      "date": "2026-04-29",
      "time": "12:30",
      "country": "US",
      "title": "Durable Goods Orders MoM",
      "impact": 3,
      "actual": "-1.4%",
      "forecast": "1.3%",
      "previous": "--",
      "unit": "%",
      "type": "manufacturing",
      "source": "tradingeconomics"
    },
    {
      "id": "US-2026-04-29-housing-starts",
      "date": "2026-04-29",
      "time": "12:30",
      "country": "US",
      "title": "Housing Starts",
      "impact": 3,
      "actual": "--",
      "forecast": "1.4M",
      "previous": "--",
      "unit": "",
      "type": "housing",
      "source": "tradingeconomics"
    },
    {
      "id": "US-2026-04-29-goods-trade-balance-adv",
      "date": "2026-04-29",
      "time": "12:30",
      "country": "US",
      "title": "Goods Trade Balance Adv",
      "impact": 2,
      "actual": "$-83.5B",
      "forecast": "$-79.0B",
      "previous": "--",
      "unit": "B",
      "type": "trade",
      "source": "tradingeconomics"
    },
    {
      "id": "US-2026-04-29-fed-interest-rate-decision",
      "date": "2026-04-29",
      "time": "18:00",
      "country": "US",
      "title": "Fed Interest Rate Decision",
      "impact": 3,
      "actual": "3.75%",
      "forecast": "--",
      "previous": "--",
      "unit": "%",
      "type": "central_bank",
      "source": "tradingeconomics"
    },
    {
      "id": "US-2026-04-29-fed-press-conference",
      "date": "2026-04-29",
      "time": "18:30",
      "country": "US",
      "title": "Fed Press Conference",
      "impact": 3,
      "actual": "--",
      "forecast": "--",
      "previous": "--",
      "unit": "",
      "type": "central_bank",
      "source": "tradingeconomics"
    },
    {
      "id": "JP-2026-04-29-industrial-production-mom-prel",
      "date": "2026-04-29",
      "time": "23:50",
      "country": "JP",
      "title": "Industrial Production MoM Prel",
      "impact": 3,
      "actual": "--",
      "forecast": "--",
      "previous": "--",
      "unit": "",
      "type": "manufacturing",
      "source": "tradingeconomics"
    },
    {
      "id": "JP-2026-04-29-industrial-production-yoy-prel",
      "date": "2026-04-29",
      "time": "23:50",
      "country": "JP",
      "title": "Industrial Production YoY Prel",
      "impact": 3,
      "actual": "--",
      "forecast": "3.3%",
      "previous": "--",
      "unit": "%",
      "type": "manufacturing",
      "source": "tradingeconomics"
    },
    {
      "id": "JP-2026-04-29-retail-sales-yoy",
      "date": "2026-04-29",
      "time": "23:50",
      "country": "JP",
      "title": "Retail Sales YoY",
      "impact": 2,
      "actual": "-0.2%",
      "forecast": "2.1%",
      "previous": "--",
      "unit": "%",
      "type": "consumer",
      "source": "tradingeconomics"
    },
    {
      "id": "JP-2026-04-29-retail-sales-mom",
      "date": "2026-04-29",
      "time": "23:50",
      "country": "JP",
      "title": "Retail Sales MoM",
      "impact": 3,
      "actual": "-2.0%",
      "forecast": "0.8%",
      "previous": "--",
      "unit": "%",
      "type": "consumer",
      "source": "tradingeconomics"
    },
    {
      "id": "CN-2026-04-30-nbs-manufacturing-pmi",
      "date": "2026-04-30",
      "time": "01:00",
      "country": "CN",
      "title": "NBS Manufacturing PMI",
      "impact": 1,
      "actual": "--",
      "forecast": "--",
      "previous": "--",
      "unit": "",
      "type": "manufacturing",
      "source": "tradingeconomics"
    },
    {
      "id": "CN-2026-04-30-nbs-non-manufacturing-pmi",
      "date": "2026-04-30",
      "time": "01:00",
      "country": "CN",
      "title": "NBS Non-Manufacturing PMI",
      "impact": 1,
      "actual": "--",
      "forecast": "--",
      "previous": "--",
      "unit": "",
      "type": "manufacturing",
      "source": "tradingeconomics"
    },
    {
      "id": "JP-2026-04-30-coincident-index-final",
      "date": "2026-04-30",
      "time": "05:00",
      "country": "JP",
      "title": "Coincident Index Final",
      "impact": 2,
      "actual": "117.9",
      "forecast": "--",
      "previous": "116.3",
      "unit": "",
      "type": "other",
      "source": "tradingeconomics"
    },
    {
      "id": "JP-2026-04-30-leading-economic-index-final",
      "date": "2026-04-30",
      "time": "05:00",
      "country": "JP",
      "title": "Leading Economic Index Final",
      "impact": 2,
      "actual": "112.1",
      "forecast": "--",
      "previous": "112.4",
      "unit": "",
      "type": "other",
      "source": "tradingeconomics"
    },
    {
      "id": "EU-2026-04-30-gdp-growth-rate-qoq-flash",
      "date": "2026-04-30",
      "time": "09:00",
      "country": "EU",
      "title": "GDP Growth Rate QoQ Flash",
      "impact": 3,
      "actual": "0.2%",
      "forecast": "0.0%",
      "previous": "--",
      "unit": "%",
      "type": "gdp",
      "source": "tradingeconomics"
    },
    {
      "id": "EU-2026-04-30-gdp-growth-rate-yoy-flash",
      "date": "2026-04-30",
      "time": "09:00",
      "country": "EU",
      "title": "GDP Growth Rate YoY Flash",
      "impact": 3,
      "actual": "1.2%",
      "forecast": "0.8%",
      "previous": "--",
      "unit": "%",
      "type": "gdp",
      "source": "tradingeconomics"
    },
    {
      "id": "EU-2026-04-30-inflation-rate-yoy-flash",
      "date": "2026-04-30",
      "time": "09:00",
      "country": "EU",
      "title": "Inflation Rate YoY Flash",
      "impact": 3,
      "actual": "--",
      "forecast": "2.9%",
      "previous": "--",
      "unit": "%",
      "type": "inflation",
      "source": "tradingeconomics"
    },
    {
      "id": "EU-2026-04-30-core-inflation-rate-yoy-flash",
      "date": "2026-04-30",
      "time": "09:00",
      "country": "EU",
      "title": "Core Inflation Rate YoY Flash",
      "impact": 3,
      "actual": "--",
      "forecast": "2.4%",
      "previous": "--",
      "unit": "%",
      "type": "inflation",
      "source": "tradingeconomics"
    },
    {
      "id": "EU-2026-04-30-unemployment-rate",
      "date": "2026-04-30",
      "time": "09:00",
      "country": "EU",
      "title": "Unemployment Rate",
      "impact": 3,
      "actual": "6.2%",
      "forecast": "6.20%",
      "previous": "--",
      "unit": "%",
      "type": "employment",
      "source": "tradingeconomics"
    },
    {
      "id": "EU-2026-04-30-ecb-interest-rate-decision",
      "date": "2026-04-30",
      "time": "12:15",
      "country": "EU",
      "title": "ECB Interest Rate Decision",
      "impact": 3,
      "actual": "2.15%",
      "forecast": "2.15%",
      "previous": "--",
      "unit": "%",
      "type": "central_bank",
      "source": "tradingeconomics"
    },
    {
      "id": "EU-2026-04-30-ecb-deposit-facility-rate",
      "date": "2026-04-30",
      "time": "12:15",
      "country": "EU",
      "title": "ECB Deposit Facility Rate",
      "impact": 3,
      "actual": "2.0%",
      "forecast": "2%",
      "previous": "--",
      "unit": "%",
      "type": "central_bank",
      "source": "tradingeconomics"
    },
    {
      "id": "US-2026-04-30-core-pce-price-index-mom",
      "date": "2026-04-30",
      "time": "12:30",
      "country": "US",
      "title": "Core PCE Price Index MoM",
      "impact": 3,
      "actual": "0.4%",
      "forecast": "--",
      "previous": "--",
      "unit": "%",
      "type": "inflation",
      "source": "tradingeconomics"
    },
    {
      "id": "US-2026-04-30-core-pce-price-index-yoy",
      "date": "2026-04-30",
      "time": "12:30",
      "country": "US",
      "title": "Core PCE Price Index YoY",
      "impact": 3,
      "actual": "3%",
      "forecast": "3.0%",
      "previous": "--",
      "unit": "%",
      "type": "inflation",
      "source": "tradingeconomics"
    },
    {
      "id": "US-2026-04-30-pce-price-index-yoy",
      "date": "2026-04-30",
      "time": "12:30",
      "country": "US",
      "title": "PCE Price Index YoY",
      "impact": 3,
      "actual": "2.8%",
      "forecast": "3.3%",
      "previous": "--",
      "unit": "%",
      "type": "inflation",
      "source": "tradingeconomics"
    },
    {
      "id": "US-2026-04-30-gdp-growth-rate-qoq-adv",
      "date": "2026-04-30",
      "time": "12:30",
      "country": "US",
      "title": "GDP Growth Rate QoQ Adv",
      "impact": 3,
      "actual": "0.5%",
      "forecast": "1.8%",
      "previous": "--",
      "unit": "%",
      "type": "gdp",
      "source": "tradingeconomics"
    },
    {
      "id": "US-2026-04-30-personal-income-mom",
      "date": "2026-04-30",
      "time": "12:30",
      "country": "US",
      "title": "Personal Income MoM",
      "impact": 3,
      "actual": "-0.1%",
      "forecast": "0.4%",
      "previous": "--",
      "unit": "%",
      "type": "consumer",
      "source": "tradingeconomics"
    },
    {
      "id": "US-2026-04-30-personal-spending-mom",
      "date": "2026-04-30",
      "time": "12:30",
      "country": "US",
      "title": "Personal Spending MoM",
      "impact": 3,
      "actual": "0.4%",
      "forecast": "0.4%",
      "previous": "--",
      "unit": "%",
      "type": "consumer",
      "source": "tradingeconomics"
    },
    {
      "id": "US-2026-04-30-employment-cost-index-qoq",
      "date": "2026-04-30",
      "time": "12:30",
      "country": "US",
      "title": "Employment Cost Index QoQ",
      "impact": 3,
      "actual": "0.7%",
      "forecast": "0.4%",
      "previous": "--",
      "unit": "%",
      "type": "employment",
      "source": "tradingeconomics"
    },
    {
      "id": "US-2026-04-30-initial-jobless-claims",
      "date": "2026-04-30",
      "time": "12:30",
      "country": "US",
      "title": "Initial Jobless Claims",
      "impact": 3,
      "actual": "--",
      "forecast": "--",
      "previous": "--",
      "unit": "",
      "type": "employment",
      "source": "tradingeconomics"
    },
    {
      "id": "EU-2026-04-30-ecb-press-conference",
      "date": "2026-04-30",
      "time": "12:45",
      "country": "EU",
      "title": "ECB Press Conference",
      "impact": 3,
      "actual": "--",
      "forecast": "--",
      "previous": "--",
      "unit": "",
      "type": "central_bank",
      "source": "tradingeconomics"
    },
    {
      "id": "US-2026-04-30-chicago-pmi",
      "date": "2026-04-30",
      "time": "13:45",
      "country": "US",
      "title": "Chicago PMI",
      "impact": 3,
      "actual": "52.8",
      "forecast": "51",
      "previous": "--",
      "unit": "",
      "type": "manufacturing",
      "source": "tradingeconomics"
    },
    {
      "id": "JP-2026-05-01-s-p-global-manufacturing-pmi-final",
      "date": "2026-05-01",
      "time": "00:30",
      "country": "JP",
      "title": "S&P Global Manufacturing PMI Final",
      "impact": 3,
      "actual": "51.6",
      "forecast": "--",
      "previous": "--",
      "unit": "",
      "type": "manufacturing",
      "source": "tradingeconomics"
    },
    {
      "id": "JP-2026-05-01-consumer-confidence",
      "date": "2026-05-01",
      "time": "05:00",
      "country": "JP",
      "title": "Consumer Confidence",
      "impact": 3,
      "actual": "33.3",
      "forecast": "--",
      "previous": "--",
      "unit": "",
      "type": "confidence",
      "source": "tradingeconomics"
    },
    {
      "id": "US-2026-05-01-s-p-global-manufacturing-pmi-final",
      "date": "2026-05-01",
      "time": "13:45",
      "country": "US",
      "title": "S&P Global Manufacturing PMI Final",
      "impact": 3,
      "actual": "52.3",
      "forecast": "--",
      "previous": "--",
      "unit": "",
      "type": "manufacturing",
      "source": "tradingeconomics"
    },
    {
      "id": "US-2026-05-01-ism-manufacturing-pmi",
      "date": "2026-05-01",
      "time": "14:00",
      "country": "US",
      "title": "ISM Manufacturing PMI",
      "impact": 3,
      "actual": "52.7",
      "forecast": "52",
      "previous": "--",
      "unit": "",
      "type": "manufacturing",
      "source": "tradingeconomics"
    },
    {
      "id": "US-2026-05-01-ism-manufacturing-prices",
      "date": "2026-05-01",
      "time": "14:00",
      "country": "US",
      "title": "ISM Manufacturing Prices",
      "impact": 1,
      "actual": "78.3",
      "forecast": "80",
      "previous": "--",
      "unit": "",
      "type": "manufacturing",
      "source": "tradingeconomics"
    },
    {
      "id": "US-2026-05-01-ism-manufacturing-employment",
      "date": "2026-05-01",
      "time": "14:00",
      "country": "US",
      "title": "ISM Manufacturing Employment",
      "impact": 1,
      "actual": "48.7",
      "forecast": "--",
      "previous": "--",
      "unit": "",
      "type": "employment",
      "source": "tradingeconomics"
    },
    {
      "id": "US-2026-05-01-ism-manufacturing-new-orders",
      "date": "2026-05-01",
      "time": "14:00",
      "country": "US",
      "title": "ISM Manufacturing New Orders",
      "impact": 1,
      "actual": "53.5",
      "forecast": "--",
      "previous": "--",
      "unit": "",
      "type": "manufacturing",
      "source": "tradingeconomics"
    },
    {
      "id": "JP-2026-05-01-unemployment-rate",
      "date": "2026-05-01",
      "time": "23:30",
      "country": "JP",
      "title": "Unemployment Rate",
      "impact": 3,
      "actual": "2.6%",
      "forecast": "2.70%",
      "previous": "--",
      "unit": "%",
      "type": "employment",
      "source": "tradingeconomics"
    },
    {
      "id": "JP-2026-05-01-jobs-applications-ratio",
      "date": "2026-05-01",
      "time": "23:30",
      "country": "JP",
      "title": "Jobs/applications ratio",
      "impact": 2,
      "actual": "1.19",
      "forecast": "--",
      "previous": "--",
      "unit": "",
      "type": "employment",
      "source": "tradingeconomics"
    },
    {
      "id": "EU-2026-05-04-s-p-global-manufacturing-pmi-final",
      "date": "2026-05-04",
      "time": "08:00",
      "country": "EU",
      "title": "S&P Global Manufacturing PMI Final",
      "impact": 3,
      "actual": "51.6",
      "forecast": "--",
      "previous": "--",
      "unit": "",
      "type": "manufacturing",
      "source": "tradingeconomics"
    },
    {
      "id": "US-2026-05-04-factory-orders-mom",
      "date": "2026-05-04",
      "time": "14:00",
      "country": "US",
      "title": "Factory Orders MoM",
      "impact": 3,
      "actual": "0%",
      "forecast": "0.8%",
      "previous": "--",
      "unit": "%",
      "type": "manufacturing",
      "source": "tradingeconomics"
    },
    {
      "id": "CN-2026-05-05-caixin-manufacturing-pmi",
      "date": "2026-05-05",
      "time": "01:45",
      "country": "CN",
      "title": "Caixin Manufacturing PMI",
      "impact": 1,
      "actual": "--",
      "forecast": "--",
      "previous": "--",
      "unit": "",
      "type": "manufacturing",
      "source": "tradingeconomics"
    },
    {
      "id": "US-2026-05-05-balance-of-trade",
      "date": "2026-05-05",
      "time": "12:30",
      "country": "US",
      "title": "Balance of Trade",
      "impact": 3,
      "actual": "$-57.3B",
      "forecast": "$-55B",
      "previous": "--",
      "unit": "B",
      "type": "trade",
      "source": "tradingeconomics"
    },
    {
      "id": "US-2026-05-05-s-p-global-composite-pmi-final",
      "date": "2026-05-05",
      "time": "13:45",
      "country": "US",
      "title": "S&P Global Composite PMI Final",
      "impact": 3,
      "actual": "50.3",
      "forecast": "--",
      "previous": "--",
      "unit": "",
      "type": "manufacturing",
      "source": "tradingeconomics"
    },
    {
      "id": "US-2026-05-05-s-p-global-services-pmi-final",
      "date": "2026-05-05",
      "time": "13:45",
      "country": "US",
      "title": "S&P Global Services PMI Final",
      "impact": 3,
      "actual": "49.8",
      "forecast": "--",
      "previous": "--",
      "unit": "",
      "type": "manufacturing",
      "source": "tradingeconomics"
    },
    {
      "id": "US-2026-05-05-ism-services-pmi",
      "date": "2026-05-05",
      "time": "14:00",
      "country": "US",
      "title": "ISM Services PMI",
      "impact": 3,
      "actual": "54.0",
      "forecast": "--",
      "previous": "--",
      "unit": "",
      "type": "manufacturing",
      "source": "tradingeconomics"
    },
    {
      "id": "US-2026-05-05-jolts-job-openings",
      "date": "2026-05-05",
      "time": "14:00",
      "country": "US",
      "title": "JOLTs Job Openings",
      "impact": 3,
      "actual": "6.882M",
      "forecast": "7M",
      "previous": "--",
      "unit": "",
      "type": "employment",
      "source": "tradingeconomics"
    },
    {
      "id": "EU-2026-05-06-s-p-global-composite-pmi-final",
      "date": "2026-05-06",
      "time": "08:00",
      "country": "EU",
      "title": "S&P Global Composite PMI Final",
      "impact": 3,
      "actual": "50.7",
      "forecast": "--",
      "previous": "--",
      "unit": "",
      "type": "manufacturing",
      "source": "tradingeconomics"
    },
    {
      "id": "EU-2026-05-06-s-p-global-services-pmi-final",
      "date": "2026-05-06",
      "time": "08:00",
      "country": "EU",
      "title": "S&P Global Services PMI Final",
      "impact": 3,
      "actual": "50.2",
      "forecast": "--",
      "previous": "--",
      "unit": "",
      "type": "manufacturing",
      "source": "tradingeconomics"
    },
    {
      "id": "EU-2026-05-06-ppi-mom",
      "date": "2026-05-06",
      "time": "09:00",
      "country": "EU",
      "title": "PPI MoM",
      "impact": 3,
      "actual": "-0.7%",
      "forecast": "0.3%",
      "previous": "--",
      "unit": "%",
      "type": "inflation",
      "source": "tradingeconomics"
    },
    {
      "id": "EU-2026-05-06-ppi-yoy",
      "date": "2026-05-06",
      "time": "09:00",
      "country": "EU",
      "title": "PPI YoY",
      "impact": 3,
      "actual": "-3%",
      "forecast": "-1.6%",
      "previous": "--",
      "unit": "%",
      "type": "inflation",
      "source": "tradingeconomics"
    },
    {
      "id": "US-2026-05-06-adp-employment-change",
      "date": "2026-05-06",
      "time": "12:15",
      "country": "US",
      "title": "ADP Employment Change",
      "impact": 3,
      "actual": "62K",
      "forecast": "70.0K",
      "previous": "--",
      "unit": "K",
      "type": "employment",
      "source": "tradingeconomics"
    },
    {
      "id": "JP-2026-05-06-boj-monetary-policy-meeting-minutes",
      "date": "2026-05-06",
      "time": "23:50",
      "country": "JP",
      "title": "BoJ Monetary Policy Meeting Minutes",
      "impact": 3,
      "actual": "--",
      "forecast": "--",
      "previous": "--",
      "unit": "",
      "type": "central_bank",
      "source": "tradingeconomics"
    },
    {
      "id": "CN-2026-05-07-caixin-services-pmi",
      "date": "2026-05-07",
      "time": "01:45",
      "country": "CN",
      "title": "Caixin Services PMI",
      "impact": 1,
      "actual": "--",
      "forecast": "--",
      "previous": "--",
      "unit": "",
      "type": "manufacturing",
      "source": "tradingeconomics"
    },
    {
      "id": "EU-2026-05-07-retail-sales-mom",
      "date": "2026-05-07",
      "time": "09:00",
      "country": "EU",
      "title": "Retail Sales MoM",
      "impact": 3,
      "actual": "-0.2%",
      "forecast": "0.4%",
      "previous": "--",
      "unit": "%",
      "type": "consumer",
      "source": "tradingeconomics"
    },
    {
      "id": "EU-2026-05-07-retail-sales-yoy",
      "date": "2026-05-07",
      "time": "09:00",
      "country": "EU",
      "title": "Retail Sales YoY",
      "impact": 2,
      "actual": "1.7%",
      "forecast": "1.4%",
      "previous": "--",
      "unit": "%",
      "type": "consumer",
      "source": "tradingeconomics"
    },
    {
      "id": "US-2026-05-07-challenger-job-cuts",
      "date": "2026-05-07",
      "time": "11:30",
      "country": "US",
      "title": "Challenger Job Cuts",
      "impact": 2,
      "actual": "60.62K",
      "forecast": "--",
      "previous": "--",
      "unit": "K",
      "type": "employment",
      "source": "tradingeconomics"
    },
    {
      "id": "US-2026-05-07-initial-jobless-claims",
      "date": "2026-05-07",
      "time": "12:30",
      "country": "US",
      "title": "Initial Jobless Claims",
      "impact": 3,
      "actual": "--",
      "forecast": "--",
      "previous": "--",
      "unit": "",
      "type": "employment",
      "source": "tradingeconomics"
    },
    {
      "id": "US-2026-05-07-nonfarm-productivity-qoq-prel",
      "date": "2026-05-07",
      "time": "12:30",
      "country": "US",
      "title": "Nonfarm Productivity QoQ Prel",
      "impact": 3,
      "actual": "1.8%",
      "forecast": "--",
      "previous": "--",
      "unit": "%",
      "type": "employment",
      "source": "tradingeconomics"
    },
    {
      "id": "US-2026-05-07-unit-labour-costs-qoq-prel",
      "date": "2026-05-07",
      "time": "12:30",
      "country": "US",
      "title": "Unit Labour Costs QoQ Prel",
      "impact": 2,
      "actual": "4.4%",
      "forecast": "--",
      "previous": "--",
      "unit": "%",
      "type": "employment",
      "source": "tradingeconomics"
    },
    {
      "id": "US-2026-05-07-construction-spending-mom",
      "date": "2026-05-07",
      "time": "14:00",
      "country": "US",
      "title": "Construction Spending MoM",
      "impact": 2,
      "actual": "-0.3%",
      "forecast": "0.4%",
      "previous": "--",
      "unit": "%",
      "type": "housing",
      "source": "tradingeconomics"
    },
    {
      "id": "JP-2026-05-08-foreign-exchange-reserves",
      "date": "2026-05-08",
      "time": "",
      "country": "JP",
      "title": "Foreign Exchange Reserves",
      "impact": 2,
      "actual": "$1374.7B",
      "forecast": "--",
      "previous": "--",
      "unit": "B",
      "type": "other",
      "source": "tradingeconomics"
    },
    {
      "id": "JP-2026-05-08-s-p-global-composite-pmi-final",
      "date": "2026-05-08",
      "time": "00:30",
      "country": "JP",
      "title": "S&P Global Composite PMI Final",
      "impact": 3,
      "actual": "53.0",
      "forecast": "--",
      "previous": "--",
      "unit": "",
      "type": "manufacturing",
      "source": "tradingeconomics"
    },
    {
      "id": "JP-2026-05-08-s-p-global-services-pmi-final",
      "date": "2026-05-08",
      "time": "00:30",
      "country": "JP",
      "title": "S&P Global Services PMI Final",
      "impact": 3,
      "actual": "53.4",
      "forecast": "--",
      "previous": "--",
      "unit": "",
      "type": "manufacturing",
      "source": "tradingeconomics"
    },
    {
      "id": "CN-2026-05-08-foreign-exchange-reserves",
      "date": "2026-05-08",
      "time": "03:00",
      "country": "CN",
      "title": "Foreign Exchange Reserves",
      "impact": 2,
      "actual": "--",
      "forecast": "--",
      "previous": "--",
      "unit": "",
      "type": "other",
      "source": "tradingeconomics"
    },
    {
      "id": "CN-2026-05-08-balance-of-trade",
      "date": "2026-05-08",
      "time": "03:00",
      "country": "CN",
      "title": "Balance of Trade",
      "impact": 3,
      "actual": "--",
      "forecast": "--",
      "previous": "--",
      "unit": "",
      "type": "trade",
      "source": "tradingeconomics"
    },
    {
      "id": "CN-2026-05-08-exports-yoy",
      "date": "2026-05-08",
      "time": "03:00",
      "country": "CN",
      "title": "Exports YoY",
      "impact": 3,
      "actual": "--",
      "forecast": "--",
      "previous": "--",
      "unit": "",
      "type": "trade",
      "source": "tradingeconomics"
    },
    {
      "id": "CN-2026-05-08-imports-yoy",
      "date": "2026-05-08",
      "time": "03:00",
      "country": "CN",
      "title": "Imports YoY",
      "impact": 3,
      "actual": "--",
      "forecast": "--",
      "previous": "--",
      "unit": "",
      "type": "trade",
      "source": "tradingeconomics"
    },
    {
      "id": "JP-2026-05-08-leading-economic-index-prel",
      "date": "2026-05-08",
      "time": "05:00",
      "country": "JP",
      "title": "Leading Economic Index Prel",
      "impact": 2,
      "actual": "--",
      "forecast": "109",
      "previous": "--",
      "unit": "",
      "type": "other",
      "source": "tradingeconomics"
    },
    {
      "id": "US-2026-05-08-non-farm-payrolls",
      "date": "2026-05-08",
      "time": "12:30",
      "country": "US",
      "title": "Non Farm Payrolls",
      "impact": 3,
      "actual": "178K",
      "forecast": "--",
      "previous": "--",
      "unit": "K",
      "type": "employment",
      "source": "tradingeconomics"
    },
    {
      "id": "US-2026-05-08-unemployment-rate",
      "date": "2026-05-08",
      "time": "12:30",
      "country": "US",
      "title": "Unemployment Rate",
      "impact": 3,
      "actual": "4.3%",
      "forecast": "--",
      "previous": "--",
      "unit": "%",
      "type": "employment",
      "source": "tradingeconomics"
    },
    {
      "id": "US-2026-05-08-average-hourly-earnings-mom",
      "date": "2026-05-08",
      "time": "12:30",
      "country": "US",
      "title": "Average Hourly Earnings MoM",
      "impact": 3,
      "actual": "0.2%",
      "forecast": "0.2%",
      "previous": "--",
      "unit": "%",
      "type": "employment",
      "source": "tradingeconomics"
    },
    {
      "id": "US-2026-05-08-average-hourly-earnings-yoy",
      "date": "2026-05-08",
      "time": "12:30",
      "country": "US",
      "title": "Average Hourly Earnings YoY",
      "impact": 3,
      "actual": "3.5%",
      "forecast": "3.6%",
      "previous": "--",
      "unit": "%",
      "type": "employment",
      "source": "tradingeconomics"
    },
    {
      "id": "US-2026-05-08-participation-rate",
      "date": "2026-05-08",
      "time": "12:30",
      "country": "US",
      "title": "Participation Rate",
      "impact": 3,
      "actual": "61.9%",
      "forecast": "--",
      "previous": "--",
      "unit": "%",
      "type": "employment",
      "source": "tradingeconomics"
    },
    {
      "id": "US-2026-05-08-michigan-consumer-sentiment-prel",
      "date": "2026-05-08",
      "time": "14:00",
      "country": "US",
      "title": "Michigan Consumer Sentiment Prel",
      "impact": 3,
      "actual": "--",
      "forecast": "--",
      "previous": "--",
      "unit": "",
      "type": "confidence",
      "source": "tradingeconomics"
    },
    {
      "id": "JP-2026-05-08-household-spending-yoy",
      "date": "2026-05-08",
      "time": "23:30",
      "country": "JP",
      "title": "Household Spending YoY",
      "impact": 2,
      "actual": "-1.8%",
      "forecast": "1.3%",
      "previous": "--",
      "unit": "%",
      "type": "consumer",
      "source": "tradingeconomics"
    },
    {
      "id": "JP-2026-05-08-average-cash-earnings-yoy",
      "date": "2026-05-08",
      "time": "23:30",
      "country": "JP",
      "title": "Average Cash Earnings YoY",
      "impact": 2,
      "actual": "3.3%",
      "forecast": "2.1%",
      "previous": "--",
      "unit": "%",
      "type": "employment",
      "source": "tradingeconomics"
    }
  ]
}